cada/__init__.py
cada/api.py
cada/assets.py
cada/commands.py
cada/csv.py
cada/models.py
cada/search.py
cada/views.py
cada/wsgi.py
cada/static/.webassets-cache/217d779071b074a0026e06d8dace2eb0
cada/static/.webassets-cache/24872015f666bdafe309e6a0e4b2dc5f
cada/static/.webassets-cache/39c057165aad1bba892594c469d3bd36
cada/static/.webassets-cache/58a04129ff9d52550ab046618f147096
cada/static/.webassets-cache/5cc1a57d96402cb3693bdeda4dde5d60
cada/static/.webassets-cache/6c3a6dc50facd648149a22559e1bbb9b
cada/static/.webassets-cache/807b2762767ab5281fd3458c743ad0ae
cada/static/.webassets-cache/9684207228a707b81573a75f90a279fe
cada/static/.webassets-cache/eaefd1a6a676f8525947ccfc078c01e3
cada/static/css/bootstrap.flatly.css
cada/static/css/cada.css
cada/static/css/cada.min.css
cada/static/fonts/glyphicons-halflings-regular.eot
cada/static/fonts/glyphicons-halflings-regular.svg
cada/static/fonts/glyphicons-halflings-regular.ttf
cada/static/fonts/glyphicons-halflings-regular.woff
cada/static/fonts/glyphicons-halflings-regular.woff2
cada/static/img/cada-screenshot.png
cada/static/img/etalab.svg
cada/static/img/logo-cada.png
cada/static/js/api.js
cada/static/js/api.min.js
cada/static/js/bootstrap.js
cada/static/js/cada.js
cada/static/js/cada.min.js
cada/static/js/jquery.js
cada/static/js/placeholders.jquery.js
cada/templates/404.html
cada/templates/about.html
cada/templates/advice.html
cada/templates/anon_alert_mail.html
cada/templates/api.html
cada/templates/base.html
cada/templates/footer.html
cada/templates/index.html
cada/templates/macros.html
cada/templates/piwik.html
cada/templates/robots.txt
cada/templates/search.html
cada/templates/sitemap.xml
cada-1.0.1.dist-info/LICENSE
cada-1.0.1.dist-info/METADATA
cada-1.0.1.dist-info/WHEEL
cada-1.0.1.dist-info/entry_points.txt
cada-1.0.1.dist-info/top_level.txt
cada-1.0.1.dist-info/RECORD
