Metadata-Version: 2.1
Name: cada
Version: 1.0.1
Summary: Search and consult CADA advices
Home-page: https://github.com/etalab/cada.data.gouv.fr
Author: Axel Haustant
Author-email: axel@data.gouv.fr
License: AGPLv3+
Keywords: cada
Classifier: Development Status :: 3 - Alpha
Classifier: Programming Language :: Python
Classifier: Environment :: Web Environment
Classifier: Operating System :: OS Independent
Classifier: Intended Audience :: Developers
Classifier: Topic :: System :: Software Distribution
Classifier: Programming Language :: Python
Classifier: Programming Language :: Python :: 2
Classifier: Programming Language :: Python :: 2.7
Classifier: Topic :: Software Development :: Libraries :: Python Modules
Classifier: License :: OSI Approved :: GNU Affero General Public License v3 or later (AGPLv3+)
Requires-Python: >=3.6
License-File: LICENSE
Requires-Dist: Flask ==1.0.2
Requires-Dist: Flask-Assets ==0.12
Requires-Dist: Flask-Mail ==0.9.1
Requires-Dist: Flask-WTF ==0.14.3
Requires-Dist: Werkzeug ==0.16.1
Requires-Dist: Jinja2 ==2.10
Requires-Dist: elasticsearch ==7.0.2
Requires-Dist: flask-mongoengine ==0.9.5
Requires-Dist: unicodecsv ==0.14.1
Requires-Dist: cssmin ==0.2.0
Requires-Dist: tqdm ==4.32.1
Requires-Dist: requests ==2.22.0
Requires-Dist: markupsafe ==2.0.1
Requires-Dist: itsdangerous ==2.0.1
Requires-Dist: WTForms ==2.3.3
Provides-Extra: report
Requires-Dist: flake8 ==3.5.0 ; extra == 'report'
Provides-Extra: sentry
Requires-Dist: raven[flask] ==6.9.0 ; extra == 'sentry'
Provides-Extra: test
Requires-Dist: pytest ==3.8.2 ; extra == 'test'
Requires-Dist: pytest-factoryboy ==2.0.1 ; extra == 'test'
Requires-Dist: pytest-flask ==0.13.0 ; extra == 'test'
